bleach_allowed_list/__init__.py
bleach_allowed_list/bleach_allowed_list.py
bleach_allowed_list-0.0.0a2.dist-info/LICENSE
bleach_allowed_list-0.0.0a2.dist-info/METADATA
bleach_allowed_list-0.0.0a2.dist-info/WHEEL
bleach_allowed_list-0.0.0a2.dist-info/top_level.txt
bleach_allowed_list-0.0.0a2.dist-info/RECORD
