Metadata-Version: 2.1
Name: bleach-allowed-list
Version: 0.0.0a2
Summary: Curated lists of tags and attributes for sanitizing html
Home-page: https://github.com/yourcelf/bleach-allowed-list.git
Author: Charlie DeTar
Author-email: cfd@media.mit.edu
License: BSD License
Platform: UNKNOWN
Classifier: Environment :: Web Environment
Classifier: Intended Audience :: Developers
Classifier: License :: OSI Approved :: BSD License
Classifier: Operating System :: OS Independent
Classifier: Programming Language :: Python
Classifier: Topic :: Internet :: WWW/HTTP
Classifier: Topic :: Internet :: WWW/HTTP :: Dynamic Content
